odoo/addons/calendar_dav/README.rst
odoo/addons/calendar_dav/__init__.py
odoo/addons/calendar_dav/__manifest__.py
odoo/addons/calendar_dav/hooks.py
odoo/addons/calendar_dav/i18n/calendar_dav.pot
odoo/addons/calendar_dav/models/__init__.py
odoo/addons/calendar_dav/models/calendar_event.py
odoo/addons/calendar_dav/readme/CONTRIBUTORS.rst
odoo/addons/calendar_dav/readme/DESCRIPTION.rst
odoo/addons/calendar_dav/static/description/icon.png
odoo/addons/calendar_dav/static/description/index.html
odoo11_addon_calendar_dav-11.0.1.0.0.99.dev7.dist-info/METADATA
odoo11_addon_calendar_dav-11.0.1.0.0.99.dev7.dist-info/WHEEL
odoo11_addon_calendar_dav-11.0.1.0.0.99.dev7.dist-info/top_level.txt
odoo11_addon_calendar_dav-11.0.1.0.0.99.dev7.dist-info/RECORD
